mdx_textalign.py
setup.py
mdx_textalign.egg-info/PKG-INFO
mdx_textalign.egg-info/SOURCES.txt
mdx_textalign.egg-info/dependency_links.txt
mdx_textalign.egg-info/requires.txt
mdx_textalign.egg-info/top_level.txt