Metadata-Version: 1.1
Name: mdx-textalign
Version: 1.0
Summary: Python-Markdown extension to support centering and right-aligning text.
Home-page: https://github.com/andrewphorn/markdown.textalign
Author: Andrew Horn
Author-email: andrewphorn@gmail.com
License: UNKNOWN
Platform: UNKNOWN
Classifier: Operating System :: OS Independent
Classifier: Intended Audience :: Developers
Classifier: Environment :: Web Environment
Classifier: Programming Language :: Python
Classifier: Topic :: Text Processing :: Filters
Classifier: Topic :: Text Processing :: Markup :: HTML
